MANIFEST.in
README.rst
setup.py
promoterExtract/__init__.py
promoterExtract/bam.py
promoterExtract/bed.py
promoterExtract/command_line.py
promoterExtract/fasta.py
promoterExtract/fastq.py
promoterExtract/gff.py
promoterExtract/maf.py
promoterExtract/parameter.py
promoterExtract/promoter.py
promoterExtract/vcf.py
promoterExtract/vcf2dadi.py
promoterExtract/vcf2fastq.py
promoterExtract.egg-info/PKG-INFO
promoterExtract.egg-info/SOURCES.txt
promoterExtract.egg-info/dependency_links.txt
promoterExtract.egg-info/requires.txt
promoterExtract.egg-info/top_level.txt