Metadata-Version: 2.1
Name: promoterExtract
Version: 0.6
Summary: Extract promoter sequence for biologists
Home-page: https://github.com/zhusitao1990
Author: zhusitao
Author-email: zhusitao1990@163.com
License: MIT
Keywords: promoter
Platform: UNKNOWN
